MarkdownParser/__init__.py
MarkdownParser/base_class.py
MarkdownParser/block_parser.py
MarkdownParser/core.py
MarkdownParser/preprocess_parser.py
MarkdownParser/tree_parser.py
markdownparser-0.5.37.dist-info/LICENSE
markdownparser-0.5.37.dist-info/METADATA
markdownparser-0.5.37.dist-info/WHEEL
markdownparser-0.5.37.dist-info/RECORD
